README.md
setup.cfg
setup.py
gaplearn/__init__.py
gaplearn.egg-info/PKG-INFO
gaplearn.egg-info/SOURCES.txt
gaplearn.egg-info/dependency_links.txt
gaplearn.egg-info/not-zip-safe
gaplearn.egg-info/requires.txt
gaplearn.egg-info/top_level.txt
gaplearn/cv/__init__.py
gaplearn/cv/searchCluster.py
gaplearn/cv/sfs.py
gaplearn/cv/utilities.py