Metadata-Version: 2.1
Name: gaplearn
Version: 0.11
Summary: Bridging gaps between other machine learning and deep learning tools and making robust, post-mortem analysis possible.
Home-page: http://github.com/awhedon/gaplearn
Author: Alexander Whedon
Author-email: alexander.whedon@gmail.com
License: MIT
Platform: UNKNOWN
